setup.py
spear.py
spear_cli.egg-info/PKG-INFO
spear_cli.egg-info/SOURCES.txt
spear_cli.egg-info/dependency_links.txt
spear_cli.egg-info/entry_points.txt
spear_cli.egg-info/requires.txt
spear_cli.egg-info/top_level.txt