Metadata-Version: 1.0
Name: spear-cli
Version: 0.0.3
Summary: Product Hunt for Hackers.
Home-page: http://github.com/karan/Spear
Author: Karan Goel
Author-email: karan@goel.im
License: MIT
Keywords: product hunt product hunt feed rss tool cli
Platform: UNKNOWN
